{"Surrounding area": [{"month": "2019-01", "def_area_ha": 3.38054, "carbon": 1011.7046382, "carbon_emission": 441.26, "forest_area": 8170.5740747044}, {"month": "2019-02", "def_area_ha": 2.40182, "carbon": 1011.4015352, "carbon_emission": 303.103, "forest_area": 8168.1722547044}, {"month": "2019-03", "def_area_ha": 1.55417, "carbon": 1011.2033785, "carbon_emission": 198.157, "forest_area": 8166.6180847044}, {"month": "2019-04", "def_area_ha": 0.81746, "carbon": 1011.0921013, "carbon_emission": 111.277, "forest_area": 8165.8006247044}, {"month": "2019-05", "def_area_ha": 0.21193, "carbon": 1011.0617017, "carbon_emission": 30.4, "forest_area": 8165.5886947044}, {"month": "2019-06", "def_area_ha": 0.14128, "carbon": 1011.0438464, "carbon_emission": 17.855, "forest_area": 8165.4474147044}, {"month": "2019-07", "def_area_ha": 0.12109, "carbon": 1011.0285056, "carbon_emission": 15.341, "forest_area": 8165.3263247044}, {"month": "2019-08", "def_area_ha": 0.80728, "carbon": 1010.9256367, "carbon_emission": 102.869, "forest_area": 8164.5190447044}, {"month": "2019-09", "def_area_ha": 1.61461, "carbon": 1010.7148464, "carbon_emission": 210.79, "forest_area": 8162.9044347044}, {"month": "2019-10", "def_area_ha": 0.75689, "carbon": 1010.6111503, "carbon_emission": 103.696, "forest_area": 8162.1475447044}, {"month": "2019-11", "def_area_ha": 1.23116, "carbon": 1010.4643411, "carbon_emission": 146.809, "forest_area": 8160.9163847044}, {"month": "2019-12", "def_area_ha": 5.56043, "carbon": 1009.7596513, "carbon_emission": 704.69, "forest_area": 8155.3559547044}, {"month": "2020-01", "def_area_ha": 7.77057, "carbon": 1020.1420829, "carbon_emission": 994.374, "forest_area": 8147.5853847044}, {"month": "2020-02", "def_area_ha": 6.35755, "carbon": 1019.3386461, "carbon_emission": 803.437, "forest_area": 8141.2278347044}, {"month": "2020-03", "def_area_ha": 12.89635, "carbon": 1017.6301256, "carbon_emission": 1708.52, "forest_area": 8128.3314847044}, {"month": "2020-04", "def_area_ha": 0.72657, "carbon": 1017.5326664, "carbon_emission": 97.459, "forest_area": 8127.6049147044}, {"month": "2020-05", "def_area_ha": 0.0, "carbon": 1017.5326664, "carbon_emission": 0.0, "forest_area": 8127.6049147044}, {"month": "2020-06", "def_area_ha": 0.111, "carbon": 1017.5175183, "carbon_emission": 15.148, "forest_area": 8127.4939147044}, {"month": "2020-07", "def_area_ha": 0.0, "carbon": 1017.5175183, "carbon_emission": 0.0, "forest_area": 8127.4939147044}, {"month": "2020-08", "def_area_ha": 0.06055, "carbon": 1017.5103931, "carbon_emission": 7.125, "forest_area": 8127.4333647044}, {"month": "2020-09", "def_area_ha": 0.0, "carbon": 1017.5103931, "carbon_emission": 0.0, "forest_area": 8127.4333647044}, {"month": "2020-10", "def_area_ha": 0.48441, "carbon": 1017.4550177, "carbon_emission": 55.375, "forest_area": 8126.9489547044}, {"month": "2020-11", "def_area_ha": 1.48343, "carbon": 1017.2675723, "carbon_emission": 187.445, "forest_area": 8125.4655247044}, {"month": "2020-12", "def_area_ha": 1.45319, "carbon": 1017.0816873, "carbon_emission": 185.885, "forest_area": 8124.0123347044}, {"month": "2021-01", "def_area_ha": 5.97401, "carbon": 1027.6896719, "carbon_emission": 760.013, "forest_area": 8118.0383247044}, {"month": "2021-02", "def_area_ha": 4.69238, "carbon": 1027.1000146, "carbon_emission": 589.657, "forest_area": 8113.3459447044}, {"month": "2021-03", "def_area_ha": 4.84374, "carbon": 1026.4915338, "carbon_emission": 608.481, "forest_area": 8108.5022047044}, {"month": "2021-04", "def_area_ha": 1.09992, "carbon": 1026.3410868, "carbon_emission": 150.447, "forest_area": 8107.4022847044}, {"month": "2021-05", "def_area_ha": 0.18163, "carbon": 1026.3264745, "carbon_emission": 14.612, "forest_area": 8107.2206547044}, {"month": "2021-06", "def_area_ha": 0.04037, "carbon": 1026.3215959, "carbon_emission": 4.879, "forest_area": 8107.1802847044}, {"month": "2021-07", "def_area_ha": 0.3431, "carbon": 1026.2769835, "carbon_emission": 44.612, "forest_area": 8106.8371847044}, {"month": "2021-08", "def_area_ha": 1.00914, "carbon": 1026.1473246, "carbon_emission": 129.659, "forest_area": 8105.8280447044}, {"month": "2021-09", "def_area_ha": 0.84767, "carbon": 1026.041725, "carbon_emission": 105.6, "forest_area": 8104.9803747044}, {"month": "2021-10", "def_area_ha": 0.0, "carbon": 1026.041725, "carbon_emission": 0.0, "forest_area": 8104.9803747044}, {"month": "2021-11", "def_area_ha": 1.47334, "carbon": 1025.864488, "carbon_emission": 177.237, "forest_area": 8103.5070347044}, {"month": "2021-12", "def_area_ha": 17.08463, "carbon": 1023.7661683, "carbon_emission": 2098.32, "forest_area": 8086.4224047044}, {"month": "2022-01", "def_area_ha": 0.0, "carbon": 1035.0882662, "carbon_emission": 0.0, "forest_area": 8086.4224047044}, {"month": "2022-02", "def_area_ha": 0.0, "carbon": 1035.0882662, "carbon_emission": 0.0, "forest_area": 8086.4224047044}, {"month": "2022-03", "def_area_ha": 64.98784, "carbon": 1026.9490271, "carbon_emission": 8139.239, "forest_area": 8021.4345647044}, {"month": "2022-04", "def_area_ha": 3.57233, "carbon": 1026.5480231, "carbon_emission": 401.004, "forest_area": 8017.8622347044}, {"month": "2022-05", "def_area_ha": 0.57524, "carbon": 1026.4813254, "carbon_emission": 66.698, "forest_area": 8017.2869947044}, {"month": "2022-06", "def_area_ha": 0.2422, "carbon": 1026.4632398, "carbon_emission": 18.086, "forest_area": 8017.0447947044}, {"month": "2022-07", "def_area_ha": 0.17156, "carbon": 1026.4450555, "carbon_emission": 18.184, "forest_area": 8016.8732347044}, {"month": "2022-08", "def_area_ha": 0.15138, "carbon": 1026.4308944, "carbon_emission": 14.161, "forest_area": 8016.7218547044}, {"month": "2022-09", "def_area_ha": 0.29265, "carbon": 1026.3963823, "carbon_emission": 34.512, "forest_area": 8016.4292047044}, {"month": "2022-10", "def_area_ha": 0.15136, "carbon": 1026.3776434, "carbon_emission": 18.739, "forest_area": 8016.2778447044}]}{"Protected area": [{"month": "2019-01", "def_area_ha": 3.38054, "carbon": 1011.7046382, "carbon_emission": 441.26, "forest_area": 8170.5740747044}, {"month": "2019-02", "def_area_ha": 2.40182, "carbon": 1011.4015352, "carbon_emission": 303.103, "forest_area": 8168.1722547044}, {"month": "2019-03", "def_area_ha": 1.55417, "carbon": 1011.2033785, "carbon_emission": 198.157, "forest_area": 8166.6180847044}, {"month": "2019-04", "def_area_ha": 0.81746, "carbon": 1011.0921013, "carbon_emission": 111.277, "forest_area": 8165.8006247044}, {"month": "2019-05", "def_area_ha": 0.21193, "carbon": 1011.0617017, "carbon_emission": 30.4, "forest_area": 8165.5886947044}, {"month": "2019-06", "def_area_ha": 0.14128, "carbon": 1011.0438464, "carbon_emission": 17.855, "forest_area": 8165.4474147044}, {"month": "2019-07", "def_area_ha": 0.12109, "carbon": 1011.0285056, "carbon_emission": 15.341, "forest_area": 8165.3263247044}, {"month": "2019-08", "def_area_ha": 0.80728, "carbon": 1010.9256367, "carbon_emission": 102.869, "forest_area": 8164.5190447044}, {"month": "2019-09", "def_area_ha": 1.61461, "carbon": 1010.7148464, "carbon_emission": 210.79, "forest_area": 8162.9044347044}, {"month": "2019-10", "def_area_ha": 0.75689, "carbon": 1010.6111503, "carbon_emission": 103.696, "forest_area": 8162.1475447044}, {"month": "2019-11", "def_area_ha": 1.23116, "carbon": 1010.4643411, "carbon_emission": 146.809, "forest_area": 8160.9163847044}, {"month": "2019-12", "def_area_ha": 5.56043, "carbon": 1009.7596513, "carbon_emission": 704.69, "forest_area": 8155.3559547044}, {"month": "2020-01", "def_area_ha": 7.77057, "carbon": 1020.1420829, "carbon_emission": 994.374, "forest_area": 8147.5853847044}, {"month": "2020-02", "def_area_ha": 6.35755, "carbon": 1019.3386461, "carbon_emission": 803.437, "forest_area": 8141.2278347044}, {"month": "2020-03", "def_area_ha": 12.89635, "carbon": 1017.6301256, "carbon_emission": 1708.52, "forest_area": 8128.3314847044}, {"month": "2020-04", "def_area_ha": 0.72657, "carbon": 1017.5326664, "carbon_emission": 97.459, "forest_area": 8127.6049147044}, {"month": "2020-05", "def_area_ha": 0.0, "carbon": 1017.5326664, "carbon_emission": 0.0, "forest_area": 8127.6049147044}, {"month": "2020-06", "def_area_ha": 0.111, "carbon": 1017.5175183, "carbon_emission": 15.148, "forest_area": 8127.4939147044}, {"month": "2020-07", "def_area_ha": 0.0, "carbon": 1017.5175183, "carbon_emission": 0.0, "forest_area": 8127.4939147044}, {"month": "2020-08", "def_area_ha": 0.06055, "carbon": 1017.5103931, "carbon_emission": 7.125, "forest_area": 8127.4333647044}, {"month": "2020-09", "def_area_ha": 0.0, "carbon": 1017.5103931, "carbon_emission": 0.0, "forest_area": 8127.4333647044}, {"month": "2020-10", "def_area_ha": 0.48441, "carbon": 1017.4550177, "carbon_emission": 55.375, "forest_area": 8126.9489547044}, {"month": "2020-11", "def_area_ha": 1.48343, "carbon": 1017.2675723, "carbon_emission": 187.445, "forest_area": 8125.4655247044}, {"month": "2020-12", "def_area_ha": 1.45319, "carbon": 1017.0816873, "carbon_emission": 185.885, "forest_area": 8124.0123347044}, {"month": "2021-01", "def_area_ha": 5.97401, "carbon": 1027.6896719, "carbon_emission": 760.013, "forest_area": 8118.0383247044}, {"month": "2021-02", "def_area_ha": 4.69238, "carbon": 1027.1000146, "carbon_emission": 589.657, "forest_area": 8113.3459447044}, {"month": "2021-03", "def_area_ha": 4.84374, "carbon": 1026.4915338, "carbon_emission": 608.481, "forest_area": 8108.5022047044}, {"month": "2021-04", "def_area_ha": 1.09992, "carbon": 1026.3410868, "carbon_emission": 150.447, "forest_area": 8107.4022847044}, {"month": "2021-05", "def_area_ha": 0.18163, "carbon": 1026.3264745, "carbon_emission": 14.612, "forest_area": 8107.2206547044}, {"month": "2021-06", "def_area_ha": 0.04037, "carbon": 1026.3215959, "carbon_emission": 4.879, "forest_area": 8107.1802847044}, {"month": "2021-07", "def_area_ha": 0.3431, "carbon": 1026.2769835, "carbon_emission": 44.612, "forest_area": 8106.8371847044}, {"month": "2021-08", "def_area_ha": 1.00914, "carbon": 1026.1473246, "carbon_emission": 129.659, "forest_area": 8105.8280447044}, {"month": "2021-09", "def_area_ha": 0.84767, "carbon": 1026.041725, "carbon_emission": 105.6, "forest_area": 8104.9803747044}, {"month": "2021-10", "def_area_ha": 0.0, "carbon": 1026.041725, "carbon_emission": 0.0, "forest_area": 8104.9803747044}, {"month": "2021-11", "def_area_ha": 1.47334, "carbon": 1025.864488, "carbon_emission": 177.237, "forest_area": 8103.5070347044}, {"month": "2021-12", "def_area_ha": 17.08463, "carbon": 1023.7661683, "carbon_emission": 2098.32, "forest_area": 8086.4224047044}, {"month": "2022-01", "def_area_ha": 0.0, "carbon": 1035.0882662, "carbon_emission": 0.0, "forest_area": 8086.4224047044}, {"month": "2022-02", "def_area_ha": 0.0, "carbon": 1035.0882662, "carbon_emission": 0.0, "forest_area": 8086.4224047044}, {"month": "2022-03", "def_area_ha": 64.98784, "carbon": 1026.9490271, "carbon_emission": 8139.239, "forest_area": 8021.4345647044}, {"month": "2022-04", "def_area_ha": 3.57233, "carbon": 1026.5480231, "carbon_emission": 401.004, "forest_area": 8017.8622347044}, {"month": "2022-05", "def_area_ha": 0.57524, "carbon": 1026.4813254, "carbon_emission": 66.698, "forest_area": 8017.2869947044}, {"month": "2022-06", "def_area_ha": 0.2422, "carbon": 1026.4632398, "carbon_emission": 18.086, "forest_area": 8017.0447947044}, {"month": "2022-07", "def_area_ha": 0.17156, "carbon": 1026.4450555, "carbon_emission": 18.184, "forest_area": 8016.8732347044}, {"month": "2022-08", "def_area_ha": 0.15138, "carbon": 1026.4308944, "carbon_emission": 14.161, "forest_area": 8016.7218547044}, {"month": "2022-09", "def_area_ha": 0.29265, "carbon": 1026.3963823, "carbon_emission": 34.512, "forest_area": 8016.4292047044}, {"month": "2022-10", "def_area_ha": 0.15136, "carbon": 1026.3776434, "carbon_emission": 18.739, "forest_area": 8016.2778447044}]}